[
  {
    "name": "wd",
    "value": "1920x1080",
    "domain": ".facebook.com",
    "path": "/",
    "expires": -1,
    "size": 11,
    "httpOnly": false,
    "secure": true,
    "session": true,
    "sameParty": false,
    "sourceScheme": "Secure",
    "sourcePort": 443
  },
  {
    "name": "m_pixel_ratio",
    "value": "1",
    "domain": ".facebook.com",
    "path": "/",
    "expires": -1,
    "size": 14,
    "httpOnly": false,
    "secure": true,
    "session": true,
    "sameParty": false,
    "sourceScheme": "Secure",
    "sourcePort": 443
  },
  {
    "name": "xs",
    "value": "31%3AZm20hEqm2bY8mw%3A2%3A1627567205%3A-1%3A1178",
    "domain": ".facebook.com",
    "path": "/",
    "expires": 1659103203.916518,
    "size": 50,
    "httpOnly": true,
    "secure": true,
    "session": false,
    "sameSite": "None",
    "sameParty": false,
    "sourceScheme": "Secure",
    "sourcePort": 443
  },
  {
    "name": "c_user",
    "value": "100002118216442",
    "domain": ".facebook.com",
    "path": "/",
    "expires": 1659103203.916448,
    "size": 21,
    "httpOnly": false,
    "secure": true,
    "session": false,
    "sameSite": "None",
    "sameParty": false,
    "sourceScheme": "Secure",
    "sourcePort": 443
  },
  {
    "name": "fr",
    "value": "12jDAqv79TYDJYXRU.AWWDz963OiPYaPaf35Vl9ahOXWw.BhArRk.Tj.AAA.0.0.BhArRk.AWUMFAc3sSA",
    "domain": ".facebook.com",
    "path": "/",
    "expires": 1635343197.916588,
    "size": 84,
    "httpOnly": true,
    "secure": true,
    "session": false,
    "sameSite": "None",
    "sameParty": false,
    "sourceScheme": "Secure",
    "sourcePort": 443
  },
  {
    "name": "sb",
    "value": "ZLQCYSZNcK6YI88qJoKn8le6",
    "domain": ".facebook.com",
    "path": "/",
    "expires": 1690639209.916332,
    "size": 26,
    "httpOnly": true,
    "secure": true,
    "session": false,
    "sameSite": "None",
    "sameParty": false,
    "sourceScheme": "Secure",
    "sourcePort": 443
  },
  {
    "name": "datr",
    "value": "Y7QCYU3gAQ6fYdLAxSaSWHbf",
    "domain": ".facebook.com",
    "path": "/",
    "expires": 1690639205.642516,
    "size": 28,
    "httpOnly": true,
    "secure": true,
    "session": false,
    "sameSite": "None",
    "sameParty": false,
    "sourceScheme": "Secure",
    "sourcePort": 443
  }
]